{
    "buttons": {
        "TOP": {
            "x": 283,
            "y": 37
        },
        "TOP_RIGHT": {
            "x": 387,
            "y": 43
        },
        "RIGHT": {
            "x": 450,
            "y": 121
        },
        "BOTTOM_RIGHT": {
            "x": 437,
            "y": 223
        },
        "BOTTOM": {
            "x": 370,
            "y": 293
        },
        "BOTTOM_LEFT": {
            "x": 294,
            "y": 345
        },
        "LEFT": {
            "x": 199,
            "y": 292
        },
        "TOP_LEFT": {
            "x": 189,
            "y": 153
        }
    },
    "screen": {
        "center": {
            "x": 326,
            "y": 188
        },
        "radius": 143
    }
}